ikarus/__init__.py
ikarus/classifier.py
ikarus/data.py
ikarus/gene_list.py
ikarus/utils.py
ikarus-0.0.3.dist-info/LICENSE
ikarus-0.0.3.dist-info/METADATA
ikarus-0.0.3.dist-info/WHEEL
ikarus-0.0.3.dist-info/top_level.txt
ikarus-0.0.3.dist-info/RECORD
